django_file_md5/__init__.py
django_file_md5/djfilemd5.py
django_file_md5-1.0.3.dist-info/METADATA
django_file_md5-1.0.3.dist-info/WHEEL
django_file_md5-1.0.3.dist-info/top_level.txt
django_file_md5-1.0.3.dist-info/RECORD
